[{"question":"58 + 56","correct":114,"answers":[112,106,105,114,121]},{"question":"51 + 51","correct":102,"answers":[102,107,92,110,103]},{"question":"54 + 50","correct":104,"answers":[107,110,104,109]},{"question":"59 + 54","correct":113,"answers":[110,116,114,113]},{"question":"55 + 59","correct":114,"answers":[114,109,111,120]},{"question":"58 + 50","correct":108,"answers":[115,113,108,105,114]},{"question":"52 + 56","correct":108,"answers":[108,115,105,117]},{"question":"55 + 57","correct":112,"answers":[108,102,112,106,103]},{"question":"56 + 57","correct":113,"answers":[113,116,114,118,105]},{"question":"57 + 54","correct":111,"answers":[107,105,111,103]}]