[{"question":"14 x 16","correct":224,"answers":[224,230,232,215]},{"question":"13 x 12","correct":156,"answers":[148,164,156,160]},{"question":"13 x 14","correct":182,"answers":[182,178,184,187]},{"question":"16 x 12","correct":192,"answers":[197,192,187,193,188]},{"question":"13 x 12","correct":156,"answers":[158,152,162,156]},{"question":"15 x 13","correct":195,"answers":[195,191,202,194,200]},{"question":"12 x 16","correct":192,"answers":[187,190,182,192]},{"question":"16 x 13","correct":208,"answers":[208,214,198,207]},{"question":"12 x 15","correct":180,"answers":[182,186,184,180]},{"question":"15 x 15","correct":225,"answers":[230,234,221,226,225]}]