[{"question":"17 x 16","correct":272,"answers":[272,268,277,269]},{"question":"16 x 17","correct":272,"answers":[274,281,272,268]},{"question":"14 x 14","correct":196,"answers":[188,190,196,191]},{"question":"15 x 18","correct":270,"answers":[270,263,261,266]},{"question":"17 x 16","correct":272,"answers":[272,280,279,268,262]},{"question":"15 x 15","correct":225,"answers":[221,234,225,222,228]},{"question":"17 x 16","correct":272,"answers":[273,272,279,266,271]},{"question":"18 x 15","correct":270,"answers":[270,273,278,261,272]},{"question":"16 x 15","correct":240,"answers":[239,230,235,240,234]},{"question":"16 x 18","correct":288,"answers":[288,286,280,294]},{"question":"18 x 15","correct":270,"answers":[277,270,264,261]},{"question":"16 x 17","correct":272,"answers":[264,272,262,267]},{"question":"14 x 16","correct":224,"answers":[218,224,221,231,216]},{"question":"17 x 15","correct":255,"answers":[256,253,257,255,249]},{"question":"16 x 15","correct":240,"answers":[240,235,241,246]},{"question":"16 x 18","correct":288,"answers":[293,286,285,284,288]},{"question":"18 x 14","correct":252,"answers":[242,247,252,256]},{"question":"16 x 18","correct":288,"answers":[279,288,295,284,281]},{"question":"18 x 15","correct":270,"answers":[273,279,272,270]},{"question":"18 x 14","correct":252,"answers":[253,252,249,255]}]