[{"question":"36 - 32","correct":4,"answers":[-3,4,5,10]},{"question":"39 - 39","correct":0,"answers":[-6,0,2,-4,-1]},{"question":"31 - 38","correct":-7,"answers":[-9,-15,-10,-16,-7]},{"question":"39 - 31","correct":8,"answers":[5,15,8,16]},{"question":"38 - 33","correct":5,"answers":[4,-4,5,13]},{"question":"33 - 37","correct":-4,"answers":[-13,-4,4,-8,-6]},{"question":"39 - 37","correct":2,"answers":[-2,-7,7,2,10]},{"question":"32 - 39","correct":-7,"answers":[-16,-13,-8,-12,-7]},{"question":"32 - 37","correct":-5,"answers":[-2,-9,-7,-5,-13]},{"question":"30 - 33","correct":-3,"answers":[1,-8,5,0,-3]}]