[{"question":"95 / 19","correct":5,"answers":[5,-1,6,9,14]},{"question":"180 / 20","correct":9,"answers":[6,5,18,0,9]},{"question":"72 / 8","correct":9,"answers":[17,9,8,13]},{"question":"24 / 8","correct":3,"answers":[-3,3,0,11]},{"question":"75 / 15","correct":5,"answers":[-3,9,6,5]},{"question":"13 / 13","correct":1,"answers":[9,1,-7,-2,5]},{"question":"15 / 15","correct":1,"answers":[-6,-1,1,6]},{"question":"54 / 6","correct":9,"answers":[17,2,16,9,14]},{"question":"20 / 20","correct":1,"answers":[1,5,3,6,4]},{"question":"80 / 10","correct":8,"answers":[10,12,13,8,9]},{"question":"144 / 18","correct":8,"answers":[9,11,10,6,8]},{"question":"15 / 3","correct":5,"answers":[-4,8,6,5]},{"question":"14 / 2","correct":7,"answers":[6,7,9,3,1]},{"question":"34 / 17","correct":2,"answers":[0,2,7,-1]},{"question":"45 / 15","correct":3,"answers":[6,5,3,4,-6]},{"question":"16 / 2","correct":8,"answers":[10,1,12,2,8]},{"question":"8 / 4","correct":2,"answers":[11,7,2,-4]},{"question":"13 / 13","correct":1,"answers":[1,-2,9,2]},{"question":"8 / 2","correct":4,"answers":[8,12,0,-2,4]},{"question":"26 / 13","correct":2,"answers":[-1,-2,-4,1,2]}]