[{"question":"6 / 6","correct":1,"answers":[-8,4,0,6,1]},{"question":"56 / 14","correct":4,"answers":[-4,13,4,-5]},{"question":"39 / 13","correct":3,"answers":[9,3,-6,10,-5]},{"question":"90 / 18","correct":5,"answers":[-3,-2,5,9,7]},{"question":"40 / 8","correct":5,"answers":[4,1,5,11]},{"question":"4 / 4","correct":1,"answers":[5,-3,3,1,0]},{"question":"140 / 20","correct":7,"answers":[-1,0,7,12]},{"question":"77 / 11","correct":7,"answers":[13,7,8,10]},{"question":"114 / 19","correct":6,"answers":[3,-1,6,2,9]},{"question":"20 / 20","correct":1,"answers":[6,-1,1,-8,3]}]