[{"question":"16 x 12","correct":192,"answers":[192,193,197,194]},{"question":"13 x 12","correct":156,"answers":[156,159,155,162]},{"question":"16 x 15","correct":240,"answers":[245,241,248,240,247]},{"question":"15 x 12","correct":180,"answers":[180,171,178,189,175]},{"question":"15 x 16","correct":240,"answers":[240,234,233,245]},{"question":"14 x 15","correct":210,"answers":[218,205,211,210,209]},{"question":"16 x 12","correct":192,"answers":[192,185,197,183]},{"question":"14 x 15","correct":210,"answers":[210,211,205,202]},{"question":"14 x 16","correct":224,"answers":[223,227,224,217]},{"question":"13 x 12","correct":156,"answers":[151,150,157,147,156]},{"question":"16 x 14","correct":224,"answers":[229,226,222,224,225]},{"question":"15 x 14","correct":210,"answers":[204,210,207,218]},{"question":"12 x 16","correct":192,"answers":[188,192,186,197,185]},{"question":"14 x 14","correct":196,"answers":[201,186,195,196]},{"question":"13 x 13","correct":169,"answers":[165,169,171,168,178]},{"question":"15 x 15","correct":225,"answers":[225,233,217,215,216]},{"question":"12 x 12","correct":144,"answers":[141,151,135,144,148]},{"question":"15 x 16","correct":240,"answers":[240,246,234,237]},{"question":"15 x 15","correct":225,"answers":[231,225,219,223,233]},{"question":"12 x 14","correct":168,"answers":[175,159,173,168]}]