[{"question":"147 - 142","correct":5,"answers":[8,2,-4,5,11]},{"question":"140 - 146","correct":-6,"answers":[0,-6,1,-4]},{"question":"146 - 145","correct":1,"answers":[8,7,1,-3,-4]},{"question":"140 - 143","correct":-3,"answers":[-12,3,-6,-3,-1]},{"question":"146 - 146","correct":0,"answers":[-4,0,2,-7,-8]},{"question":"140 - 143","correct":-3,"answers":[-3,5,-1,4]},{"question":"142 - 146","correct":-4,"answers":[-13,-6,-10,-4]},{"question":"145 - 149","correct":-4,"answers":[-4,-12,-3,-10,3]},{"question":"149 - 140","correct":9,"answers":[18,9,1,4,6]},{"question":"140 - 146","correct":-6,"answers":[-8,-6,-7,-9]},{"question":"141 - 148","correct":-7,"answers":[-7,1,-15,-5]},{"question":"147 - 149","correct":-2,"answers":[1,5,-7,-2,-1]},{"question":"142 - 142","correct":0,"answers":[-1,1,0,9]},{"question":"146 - 143","correct":3,"answers":[-4,2,3,9]},{"question":"146 - 146","correct":0,"answers":[9,3,0,1,2]},{"question":"147 - 144","correct":3,"answers":[8,-1,2,3]},{"question":"142 - 149","correct":-7,"answers":[-6,-9,-16,-7,-15]},{"question":"148 - 142","correct":6,"answers":[6,8,2,10]},{"question":"148 - 147","correct":1,"answers":[0,-7,-5,1,2]},{"question":"145 - 142","correct":3,"answers":[-4,-5,3,0,2]}]