[{"answers":[-6,5,-5,0,1],"question":"0 // 8","correct":0},{"answers":[7,0,-9,4],"question":"24 // 12","correct":0},{"answers":[0,8,7,-2,9],"question":"0 // 9","correct":0},{"answers":[-5,5,-8,-4,0],"question":"7 // 1","correct":0},{"answers":[-9,0,9,-5],"question":"49 // 7","correct":0},{"answers":[0,-2,-4,7],"question":"20 // 5","correct":0},{"answers":[-8,8,-3,0,-5],"question":"26 // 13","correct":0},{"answers":[-8,0,-3,-6],"question":"117 // 13","correct":0},{"answers":[6,7,-7,0,9],"question":"4 // 2","correct":0},{"answers":[0,-7,-4,2],"question":"24 // 6","correct":0}]